edge_api_client/__init__.py
edge_api_client/base.py
edge_api_client/edge.py
edge_api_client/utilities/__init__.py
edge_api_client/utilities/funcs.py
edge_api_client/utilities/schemas.py
api_client_lnx_edge-0.3.11.dist-info/METADATA
api_client_lnx_edge-0.3.11.dist-info/WHEEL
api_client_lnx_edge-0.3.11.dist-info/top_level.txt
api_client_lnx_edge-0.3.11.dist-info/RECORD
