Metadata-Version: 2.1
Name: api-client-lnx-edge
Version: 0.3.11
Summary: Client for the LNX Edge API
Home-page: https://github.com/Lnmix/edge_api_client
Author: Nick Tulli
Author-email: ntulli@leadnomics.com
Classifier: Programming Language :: Python :: 3
Classifier: Operating System :: OS Independent
Requires-Python: >=3.7
Requires-Dist: pytz >=2021.1
Requires-Dist: requests >=2.25.1
Requires-Dist: marshmallow ==3.18.0
